{
  "crawler_info": {
    "version": "2.0 Enhanced",
    "crawl_method": "stealth_mode",
    "crawled_at": "2025-07-17T22:52:25.235610",
    "complex_id": "1158"
  },
  "basic_info": {
    "complex_id": "1158",
    "source_url": "https://new.land.naver.com/complexes/1158",
    "extracted_at": "2025-07-17T22:52:19.478839",
    "url": "https://new.land.naver.com/complexes/1158?ms=37.586819,126.936574,17&a=APT:ABYG:JGC:PRE&e=RETAIL",
    "title": "네이버페이 부동산",
    "timestamp": "2025-07-17T13:52:17.172Z",
    "complexId": "1158"
  },
  "current_listings": [
    {
      "index": 0,
      "selector": ".item_link",
      "text": "집주인중앙하이츠 101동매매5억 3,000아파트83/59m², 저/16층, 동향입주물건 수리되어내부깨끗 평지에위치 단지앞마을버스운행",
      "price": "5억 3",
      "area": null,
      "floor": "16층",
      "deal_type": "매매",
      "extracted_at": "2025-07-17T13:52:19.491Z"
    },
    {
      "index": 1,
      "selector": ".item_link",
      "text": "집주인중앙하이츠 101동매매7억아파트111A/84m², 9/16층, 남향정남향 확트인 조망 구조 좋음 깔금한 시설상태",
      "price": "7억",
      "area": null,
      "floor": "16층",
      "deal_type": "매매",
      "extracted_at": "2025-07-17T13:52:19.491Z"
    },
    {
      "index": 31,
      "selector": "[class*=\"item\"]",
      "text": "전체면적㎡평전체83㎡111C㎡111A㎡111B㎡138㎡151㎡",
      "price": null,
      "area": "83㎡",
      "floor": null,
      "deal_type": null,
      "extracted_at": "2025-07-17T13:52:19.491Z"
    },
    {
      "index": 42,
      "selector": "[class*=\"item\"]",
      "text": "집주인중앙하이츠 101동매매5억 3,000아파트83/59m², 저/16층, 동향입주물건 수리되어내부깨끗 평지에위치 단지앞마을버스운행알터 제공벽산공인중개사사무소확인매물 25.07.01.집주인중앙하이츠 101동매매7억아파트111A/84m², 9/16층, 남향정남향 확트인 조망 구조 좋음 깔금한 시설상태알터 제공금호어울림공인중개사사무소확인매물 25.06.20.",
      "price": "5억 3",
      "area": null,
      "floor": "16층",
      "deal_type": "매매",
      "extracted_at": "2025-07-17T13:52:19.492Z"
    },
    {
      "index": 0,
      "selector": "[class*=\"deal\"]",
      "text": "거래방식거래방식전체매매전세월세단기임대중복선택이 가능합니다.전체",
      "price": null,
      "area": null,
      "floor": null,
      "deal_type": "매매",
      "extracted_at": "2025-07-17T13:52:19.493Z"
    },
    {
      "index": 3,
      "selector": "[class*=\"deal\"]",
      "text": "초원드림빌면적 - ㎡41.47㎡ ~ 87.08㎡단지정보시세/실거래가",
      "price": null,
      "area": "41.47㎡",
      "floor": null,
      "deal_type": null,
      "extracted_at": "2025-07-17T13:52:19.493Z"
    },
    {
      "index": 4,
      "selector": "[class*=\"deal\"]",
      "text": "동일1차면적96.82㎡63.31㎡ ~ 96.82㎡단지정보시세/실거래가",
      "price": null,
      "area": "96.82㎡",
      "floor": null,
      "deal_type": null,
      "extracted_at": "2025-07-17T13:52:19.493Z"
    },
    {
      "index": 5,
      "selector": "[class*=\"deal\"]",
      "text": "럭키힐면적100.92㎡100.92㎡ ~ 100.94㎡단지정보시세/실거래가",
      "price": null,
      "area": "100.92㎡",
      "floor": null,
      "deal_type": null,
      "extracted_at": "2025-07-17T13:52:19.493Z"
    },
    {
      "index": 6,
      "selector": "[class*=\"deal\"]",
      "text": "서부사이버면적79.13㎡56.2㎡ ~ 115.58㎡단지정보시세/실거래가",
      "price": null,
      "area": "79.13㎡",
      "floor": null,
      "deal_type": null,
      "extracted_at": "2025-07-17T13:52:19.493Z"
    },
    {
      "index": 7,
      "selector": "[class*=\"deal\"]",
      "text": "동일5차면적100.35㎡67.73㎡ ~ 127.64㎡단지정보시세/실거래가",
      "price": null,
      "area": "100.35㎡",
      "floor": null,
      "deal_type": null,
      "extracted_at": "2025-07-17T13:52:19.493Z"
    },
    {
      "index": 8,
      "selector": "[class*=\"deal\"]",
      "text": "1,878만서강매매10억10억면적176㎡176.73㎡ ~ 176.73㎡매매매물만 보기1개 매물이 있습니다.단지정보시세/실거래가",
      "price": "10억10",
      "area": "176㎡",
      "floor": null,
      "deal_type": "매매",
      "extracted_at": "2025-07-17T13:52:19.493Z"
    },
    {
      "index": 9,
      "selector": "[class*=\"deal\"]",
      "text": "4,565만홍제매매2.9억2.8억~3.5억월세35만35만면적21㎡21.55㎡ ~ 21.55㎡매매매물만 보기5개 매물이 있습니다.월세매물만 보기1개 매물이 있습니다.단지정보",
      "price": "9억2",
      "area": "21㎡",
      "floor": null,
      "deal_type": "매매",
      "extracted_at": "2025-07-17T13:52:19.493Z"
    },
    {
      "index": 10,
      "selector": "[class*=\"deal\"]",
      "text": "제일면적105.82㎡69.4㎡ ~ 105.82㎡단지정보시세/실거래가",
      "price": null,
      "area": "105.82㎡",
      "floor": null,
      "deal_type": null,
      "extracted_at": "2025-07-17T13:52:19.493Z"
    },
    {
      "index": 11,
      "selector": "[class*=\"deal\"]",
      "text": "힐탑면적37.74㎡34.04㎡ ~ 103.16㎡단지정보시세/실거래가",
      "price": null,
      "area": "37.74㎡",
      "floor": null,
      "deal_type": null,
      "extracted_at": "2025-07-17T13:52:19.493Z"
    },
    {
      "index": 12,
      "selector": "[class*=\"deal\"]",
      "text": "도양라비앙면적70.05㎡52.34㎡ ~ 118.06㎡단지정보시세/실거래가",
      "price": null,
      "area": "70.05㎡",
      "floor": null,
      "deal_type": null,
      "extracted_at": "2025-07-17T13:52:19.493Z"
    },
    {
      "index": 13,
      "selector": "[class*=\"deal\"]",
      "text": "2,085만중앙하이츠매매7억5.3억~7억면적111㎡83.87㎡ ~ 111.21㎡매매매물만 보기2개 매물이 있습니다.단지정보시세/실거래가",
      "price": "7억5",
      "area": "111㎡",
      "floor": null,
      "deal_type": "매매",
      "extracted_at": "2025-07-17T13:52:19.493Z"
    },
    {
      "index": 14,
      "selector": "[class*=\"deal\"]",
      "text": "1,719만나눔스타빌매매5.2억5.2억~5.3억면적100㎡100.78㎡ ~ 100.78㎡매매매물만 보기3개 매물이 있습니다.단지정보시세/실거래가",
      "price": "2억5",
      "area": "100㎡",
      "floor": null,
      "deal_type": "매매",
      "extracted_at": "2025-07-17T13:52:19.493Z"
    },
    {
      "index": 15,
      "selector": "[class*=\"deal\"]",
      "text": "1,783만엠씨케이(MCK)파크힐매매5.5억5.5억면적102㎡102.91㎡ ~ 102.91㎡매매매물만 보기1개 매물이 있습니다.단지정보시세/실거래가",
      "price": "5억5",
      "area": "102㎡",
      "floor": null,
      "deal_type": "매매",
      "extracted_at": "2025-07-17T13:52:19.493Z"
    },
    {
      "index": 16,
      "selector": "[class*=\"deal\"]",
      "text": "서울맨션면적54.94㎡41.52㎡ ~ 76.99㎡단지정보시세/실거래가",
      "price": null,
      "area": "54.94㎡",
      "floor": null,
      "deal_type": null,
      "extracted_at": "2025-07-17T13:52:19.493Z"
    },
    {
      "index": 17,
      "selector": "[class*=\"deal\"]",
      "text": "굿모닝하이츠면적77.01㎡62.6㎡ ~ 80.15㎡단지정보시세/실거래가",
      "price": null,
      "area": "77.01㎡",
      "floor": null,
      "deal_type": null,
      "extracted_at": "2025-07-17T13:52:19.493Z"
    },
    {
      "index": 18,
      "selector": "[class*=\"deal\"]",
      "text": "동평모임빌늘푸른면적101.37㎡101.37㎡ ~ 179.34㎡단지정보시세/실거래가",
      "price": null,
      "area": "101.37㎡",
      "floor": null,
      "deal_type": null,
      "extracted_at": "2025-07-17T13:52:19.493Z"
    },
    {
      "index": 19,
      "selector": "[class*=\"deal\"]",
      "text": "해성훼미리면적108.36㎡108.36㎡ ~ 193.67㎡단지정보시세/실거래가",
      "price": null,
      "area": "108.36㎡",
      "floor": null,
      "deal_type": null,
      "extracted_at": "2025-07-17T13:52:19.493Z"
    },
    {
      "index": 20,
      "selector": "[class*=\"deal\"]",
      "text": "2,589만홍제맨션매매6.5억6.5억면적83㎡83.01㎡ ~ 83.01㎡매매매물만 보기1개 매물이 있습니다.단지정보시세/실거래가",
      "price": "5억6",
      "area": "83㎡",
      "floor": null,
      "deal_type": "매매",
      "extracted_at": "2025-07-17T13:52:19.493Z"
    },
    {
      "index": 21,
      "selector": "[class*=\"deal\"]",
      "text": "2,038만조한매매6.35억6.3억~6.8억면적103㎡103.75㎡ ~ 104.72㎡매매매물만 보기3개 매물이 있습니다.단지정보시세/실거래가",
      "price": "35억6",
      "area": "103㎡",
      "floor": null,
      "deal_type": "매매",
      "extracted_at": "2025-07-17T13:52:19.493Z"
    },
    {
      "index": 22,
      "selector": "[class*=\"deal\"]",
      "text": "2,024만동일4차매매6억6억전세-2.85억면적98㎡96.84㎡ ~ 98.58㎡매매매물만 보기1개 매물이 있습니다.전세매물만 보기2개 매물이 있습니다.단지정보시세/실거래가",
      "price": "6억6",
      "area": "98㎡",
      "floor": null,
      "deal_type": "매매",
      "extracted_at": "2025-07-17T13:52:19.493Z"
    },
    {
      "index": 23,
      "selector": "[class*=\"deal\"]",
      "text": "동일3차면적94.08㎡93.98㎡ ~ 134.79㎡단지정보시세/실거래가",
      "price": null,
      "area": "94.08㎡",
      "floor": null,
      "deal_type": null,
      "extracted_at": "2025-07-17T13:52:19.493Z"
    },
    {
      "index": 24,
      "selector": "[class*=\"deal\"]",
      "text": "2,730만홍제금호어울림매매9억8.5억~10억전세-6억~6.5억월세1.6백1.6백면적109㎡80.94㎡ ~ 110.81㎡매매매물만 보기41개 매물이 있습니다.전세매물만 보기2개 매물이 있습니다.월세매물만 보기3개 매물이 있습니다.단지정보시세/실거래가",
      "price": "9억8",
      "area": "109㎡",
      "floor": null,
      "deal_type": "매매",
      "extracted_at": "2025-07-17T13:52:19.493Z"
    },
    {
      "index": 25,
      "selector": "[class*=\"deal\"]",
      "text": "그랜드면적66.36㎡56.79㎡ ~ 70.64㎡단지정보시세/실거래가",
      "price": null,
      "area": "66.36㎡",
      "floor": null,
      "deal_type": null,
      "extracted_at": "2025-07-17T13:52:19.493Z"
    },
    {
      "index": 27,
      "selector": "[class*=\"deal\"]",
      "text": "동일2차면적93.89㎡67.92㎡ ~ 109.11㎡단지정보시세/실거래가",
      "price": null,
      "area": "93.89㎡",
      "floor": null,
      "deal_type": null,
      "extracted_at": "2025-07-17T13:52:19.493Z"
    },
    {
      "index": 28,
      "selector": "[class*=\"deal\"]",
      "text": "월드뷰월세1.3백1.3백면적96㎡96.13㎡ ~ 96.13㎡월세매물만 보기1개 매물이 있습니다.단지정보시세/실거래가",
      "price": null,
      "area": "96㎡",
      "floor": null,
      "deal_type": "월세",
      "extracted_at": "2025-07-17T13:52:19.493Z"
    },
    {
      "index": 30,
      "selector": "[class*=\"deal\"]",
      "text": "3,088만홍제현대매매8.5억6.6억~11.5억전세5억5억~7.5억월세-80만면적91㎡71.81㎡ ~ 138.88㎡매매매물만 보기41개 매물이 있습니다.전세매물만 보기30개 매물이 있습니다.월세매물만 보기3개 매물이 있습니다.단지정보시세/실거래가",
      "price": "5억6",
      "area": "91㎡",
      "floor": null,
      "deal_type": "매매",
      "extracted_at": "2025-07-17T13:52:19.493Z"
    }
  ],
  "transaction_history": [],
  "statistics": {
    "total_listings": 31,
    "total_transactions": 0,
    "data_quality": "enhanced"
  },
  "files": {
    "screenshot": "data/output/enhanced_screenshot_1158_20250717_225225.png"
  }
}