{
  "crawler_info": {
    "version": "2.0 Enhanced",
    "crawl_method": "stealth_mode",
    "crawled_at": "2025-07-18T00:06:52.298100",
    "complex_id": "1402"
  },
  "basic_info": {
    "complex_id": "1402",
    "source_url": "https://new.land.naver.com/complexes/1402",
    "extracted_at": "2025-07-18T00:06:48.331092",
    "url": "https://new.land.naver.com/complexes/1402?ms=37.495763,126.754371,17&a=APT:ABYG:JGC:PRE&e=RETAIL",
    "title": "네이버페이 부동산",
    "timestamp": "2025-07-17T15:06:46.508Z",
    "complexId": "1402"
  },
  "current_listings": [
    {
      "index": 0,
      "selector": ".item_link",
      "text": "집주인한아름동원 1536동매매5억 1,000아파트105/84m², 13/19층, 동향탁 트인 뷰,편리한 교통환경,깨끗하게 관리잘 된 집,가격조정가능해요",
      "price": "5억 1",
      "area": null,
      "floor": "19층",
      "deal_type": "매매",
      "extracted_at": "2025-07-17T15:06:48.341Z"
    },
    {
      "index": 2,
      "selector": ".item_link",
      "text": "집주인한아름동원 1535동매매5억아파트105/84m², 1/19층, 남향매매가조정 세안고 26년9월만기 내부샷시포함올수리 중문 남향",
      "price": "5억",
      "area": null,
      "floor": "19층",
      "deal_type": "매매",
      "extracted_at": "2025-07-17T15:06:48.341Z"
    },
    {
      "index": 4,
      "selector": ".item_link",
      "text": "집주인한아름동원 1536동매매5억아파트105/84m², 9/19층, 동향내부샷시포함 구 올수리. 이사정상 협의",
      "price": "5억",
      "area": null,
      "floor": "19층",
      "deal_type": "매매",
      "extracted_at": "2025-07-17T15:06:48.341Z"
    },
    {
      "index": 5,
      "selector": ".item_link",
      "text": "집주인한아름동원 1535동매매4억 5,000아파트105/84m², 1/19층, 동향세안고,샷시 포함 올수리. 채광 좋은 1층. 아이들 맘 편히 키우세요",
      "price": "4억 5",
      "area": null,
      "floor": "19층",
      "deal_type": "매매",
      "extracted_at": "2025-07-17T15:06:48.341Z"
    },
    {
      "index": 8,
      "selector": ".item_link",
      "text": "집주인한아름동원 1535동매매5억 3,000아파트105/84m², 3/19층, 남향추천.  샷시포함 내부올수리 . 입주가능",
      "price": "5억 3",
      "area": null,
      "floor": "19층",
      "deal_type": "매매",
      "extracted_at": "2025-07-17T15:06:48.341Z"
    },
    {
      "index": 9,
      "selector": ".item_link",
      "text": "집주인한아름동원 1535동매매5억 3,000아파트105/84m², 19/19층, 남향로얄동, 진짜 예쁜 인테리어, 층간소음에서 해방, 강추합니다.",
      "price": "5억 3",
      "area": null,
      "floor": "19층",
      "deal_type": "매매",
      "extracted_at": "2025-07-17T15:06:48.341Z"
    },
    {
      "index": 10,
      "selector": ".item_link",
      "text": "집주인한아름동원 1535동매매5억 2,000아파트105/84m², 9/19층, 동향샷시포함 내부 올수리, 세안고 갭투자 가능함.",
      "price": "5억 2",
      "area": null,
      "floor": "19층",
      "deal_type": "매매",
      "extracted_at": "2025-07-17T15:06:48.341Z"
    },
    {
      "index": 14,
      "selector": ".item_link",
      "text": "집주인한아름동원 1536동매매5억 1,000아파트105/84m², 18/19층, 남향시원한 뷰, 거실 확장형, 샷시포함 올수리된 집으로 깔끔합니다.",
      "price": "5억 1",
      "area": null,
      "floor": "19층",
      "deal_type": "매매",
      "extracted_at": "2025-07-17T15:06:48.341Z"
    },
    {
      "index": 16,
      "selector": ".item_link",
      "text": "집주인한아름동원 1535동매매5억 5,000아파트105/84m², 2/19층, 남향강추 입주가능. 외부샷시까지 올수리 . 정남향.주변인프라우수.이사협의",
      "price": "5억 5",
      "area": null,
      "floor": "19층",
      "deal_type": "매매",
      "extracted_at": "2025-07-17T15:06:48.341Z"
    },
    {
      "index": 17,
      "selector": ".item_link",
      "text": "집주인한아름동원 1536동매매4억 9,800아파트105/84m², 고/19층, 동향샷시포함 올수리. 교통이 편리한 주변환경",
      "price": "4억 9",
      "area": null,
      "floor": "19층",
      "deal_type": "매매",
      "extracted_at": "2025-07-17T15:06:48.341Z"
    },
    {
      "index": 19,
      "selector": ".item_link",
      "text": "집주인한아름동원 1537동매매3억 6,000아파트78/59m², 2/12층, 남향귀한 남향동, 세안고 , 교통편한 단지",
      "price": "3억 6",
      "area": null,
      "floor": "12층",
      "deal_type": "매매",
      "extracted_at": "2025-07-17T15:06:48.341Z"
    },
    {
      "index": 41,
      "selector": "[class*=\"item\"]",
      "text": "집주인한아름동원 1536동매매5억 1,000아파트105/84m², 13/19층, 동향탁 트인 뷰,편리한 교통환경,깨끗하게 관리잘 된 집,가격조정가능해요부동산뱅크 제공제일공인중개사사무소확인매물 25.07.17.집주인한아름동원 1536동매매5억 1,000아파트105/84m², 13/19층, 동향추천,시원한뻥뷰,내부수리되어 깨끗한 입주협의 가능한 집매경부동산 제공부자공인중개사사무소확인매물 25.07.17.집주인한아름동원 1535동매매5억아파트105/84m², 1/19층, 남향매매가조정 세안고 26년9월만기 내부샷시포함올수리 중문 남향  ",
      "price": "5억 1",
      "area": null,
      "floor": "19층",
      "deal_type": "매매",
      "extracted_at": "2025-07-17T15:06:48.342Z"
    }
  ],
  "transaction_history": [],
  "statistics": {
    "total_listings": 12,
    "total_transactions": 0,
    "data_quality": "enhanced"
  },
  "files": {
    "screenshot": "data/output/enhanced_screenshot_1402_20250718_000652.png"
  }
}