{
  "crawler_info": {
    "version": "2.0 Enhanced",
    "crawl_method": "stealth_mode",
    "crawled_at": "2025-07-18T02:14:30.953743",
    "complex_id": "1774"
  },
  "basic_info": {
    "complex_id": "1774",
    "source_url": "https://new.land.naver.com/complexes/1774",
    "extracted_at": "2025-07-18T02:14:26.468441",
    "url": "https://new.land.naver.com/complexes/1774?ms=37.279,126.95366,17&a=APT:ABYG:JGC:PRE&e=RETAIL",
    "title": "네이버페이 부동산",
    "timestamp": "2025-07-17T17:14:25.019Z",
    "complexId": "1774"
  },
  "current_listings": [
    {
      "index": 0,
      "selector": ".item_link",
      "text": "집주인강남 103동매매3억 8,000아파트107/84m², 17/19층, 남향",
      "price": "3억 8",
      "area": null,
      "floor": "19층",
      "deal_type": "매매",
      "extracted_at": "2025-07-17T17:14:26.477Z"
    },
    {
      "index": 1,
      "selector": ".item_link",
      "text": "집주인강남 108동매매4억아파트107/84m², 15/20층, 남향전세안고, 깔끔수리된 집, 전망굿, 초품아",
      "price": "4억",
      "area": null,
      "floor": "20층",
      "deal_type": "매매",
      "extracted_at": "2025-07-17T17:14:26.477Z"
    },
    {
      "index": 2,
      "selector": ".item_link",
      "text": "집주인강남 108동매매3억 7,500아파트107/84m², 6/20층, 남향깨끗한 남향집. 로얄동. 호매실역초역세권. 홈플러스와 중심상권이 7분거리",
      "price": "3억 7",
      "area": null,
      "floor": "20층",
      "deal_type": "매매",
      "extracted_at": "2025-07-17T17:14:26.477Z"
    },
    {
      "index": 3,
      "selector": ".item_link",
      "text": "집주인강남 102동매매2억 9,000아파트85/59m², 12/20층, 동향신분당선 초역세권,수리된 전망좋은 집",
      "price": "2억 9",
      "area": null,
      "floor": "20층",
      "deal_type": "매매",
      "extracted_at": "2025-07-17T17:14:26.477Z"
    },
    {
      "index": 4,
      "selector": ".item_link",
      "text": "집주인강남 109동매매3억 8,500아파트107/84m², 5/20층, 동향신분당선 호매실역 초역세권,샷시포함 올수리",
      "price": "3억 8",
      "area": null,
      "floor": "20층",
      "deal_type": "매매",
      "extracted_at": "2025-07-17T17:14:26.477Z"
    },
    {
      "index": 5,
      "selector": ".item_link",
      "text": "집주인강남 102동매매3억아파트85/59m², 13/20층, 동향신분당선 초역세권,전망 최고의 수리된 집,전세안고",
      "price": "3억",
      "area": null,
      "floor": "20층",
      "deal_type": "매매",
      "extracted_at": "2025-07-17T17:14:26.477Z"
    },
    {
      "index": 6,
      "selector": ".item_link",
      "text": "집주인강남 105동매매4억아파트107/84m², 8/20층, 남향신분당선 초역세권,전망좋은 선호동",
      "price": "4억",
      "area": null,
      "floor": "20층",
      "deal_type": "매매",
      "extracted_at": "2025-07-17T17:14:26.477Z"
    },
    {
      "index": 7,
      "selector": ".item_link",
      "text": "집주인강남 101동매매2억 8,500아파트85/59m², 8/20층, 동향신분당선 초역세권,올수리,세안고 투자적합",
      "price": "2억 8",
      "area": null,
      "floor": "20층",
      "deal_type": "매매",
      "extracted_at": "2025-07-17T17:14:26.477Z"
    },
    {
      "index": 8,
      "selector": ".item_link",
      "text": "집주인강남 102동매매3억 2,000아파트85/59m², 17/20층, 동향샷시포함올수리.깨끗하고전망좋음.호매실역초역세권",
      "price": "3억 2",
      "area": null,
      "floor": "20층",
      "deal_type": "매매",
      "extracted_at": "2025-07-17T17:14:26.477Z"
    },
    {
      "index": 9,
      "selector": ".item_link",
      "text": "집주인강남 106동매매2억 8,000아파트85/59m², 7/20층, 동향깨끗한 집. 홈플러스와 중심상권이 7분거리. 주인거주",
      "price": "2억 8",
      "area": null,
      "floor": "20층",
      "deal_type": "매매",
      "extracted_at": "2025-07-17T17:14:26.477Z"
    },
    {
      "index": 10,
      "selector": ".item_link",
      "text": "집주인강남 107동매매3억 9,000아파트107/84m², 11/18층, 남향샷시제외 올수리. 호매실역 초역세권. 홈플러스와 중심상권이 7분거리",
      "price": "3억 9",
      "area": null,
      "floor": "18층",
      "deal_type": "매매",
      "extracted_at": "2025-07-17T17:14:26.477Z"
    },
    {
      "index": 11,
      "selector": ".item_link",
      "text": "집주인강남 108동월세5,000/95아파트107/84m², 9/20층, 남향수리된 깨끗한집. 홈플러스와 중심상권이 7분거리 탁 트인 뷰",
      "price": null,
      "area": null,
      "floor": "20층",
      "deal_type": "월세",
      "extracted_at": "2025-07-17T17:14:26.477Z"
    },
    {
      "index": 12,
      "selector": ".item_link",
      "text": "집주인강남 103동매매3억 6,000아파트107/84m², 8/19층, 남향깨끗한 남향집. 호매실역 초역세권. 홈플러스와 중심상권이 7분거리",
      "price": "3억 6",
      "area": null,
      "floor": "19층",
      "deal_type": "매매",
      "extracted_at": "2025-07-17T17:14:26.477Z"
    },
    {
      "index": 13,
      "selector": ".item_link",
      "text": "집주인강남 105동월세3,000/100아파트107/84m², 6/20층, 남향교통,편의시설 이용 편리하고 수리된 집",
      "price": null,
      "area": null,
      "floor": "20층",
      "deal_type": "월세",
      "extracted_at": "2025-07-17T17:14:26.477Z"
    }
  ],
  "transaction_history": [],
  "statistics": {
    "total_listings": 14,
    "total_transactions": 0,
    "data_quality": "enhanced"
  },
  "files": {
    "screenshot": "data/output/enhanced_screenshot_1774_20250718_021430.png"
  }
}