{
  "crawler_info": {
    "version": "2.0 Enhanced",
    "crawl_method": "stealth_mode",
    "crawled_at": "2025-07-18T20:28:50.228406",
    "complex_id": "10203"
  },
  "basic_info": {
    "complex_id": "10203",
    "source_url": "https://new.land.naver.com/complexes/10203",
    "extracted_at": "2025-07-18T20:28:44.611650",
    "url": "https://new.land.naver.com/complexes/10203?ms=37.369876,127.105527,17&a=APT:ABYG:JGC:PRE&e=RETAIL",
    "title": "네이버페이 부동산",
    "timestamp": "2025-07-18T11:28:42.457Z",
    "complexId": "10203"
  },
  "current_listings": [
    {
      "index": 0,
      "selector": ".item_link",
      "text": "성원상떼뷰(주상복합) 201동전세13억아파트167/144m², 4/16층, 남동향54타입 풀옵션 카페거리전망 정상입주 쾌적한집",
      "price": "13억",
      "area": null,
      "floor": "16층",
      "deal_type": "전세",
      "extracted_at": "2025-07-18T11:28:44.621Z"
    },
    {
      "index": 1,
      "selector": ".item_link",
      "text": "성원상떼뷰(주상복합) 201동매매19억아파트167/144m², 14/16층, 남동향전세안고 전망굿 풀옵션 완전깨끗",
      "price": "19억",
      "area": null,
      "floor": "16층",
      "deal_type": "매매",
      "extracted_at": "2025-07-18T11:28:44.621Z"
    },
    {
      "index": 4,
      "selector": ".item_link",
      "text": "성원상떼뷰(주상복합) 101동매매30억아파트187/158m², 2/17층, 남동향주택같은정원굿 천천히 입주",
      "price": "30억",
      "area": null,
      "floor": "17층",
      "deal_type": "매매",
      "extracted_at": "2025-07-18T11:28:44.621Z"
    },
    {
      "index": 7,
      "selector": ".item_link",
      "text": "성원상떼뷰(주상복합) 201동매매20억아파트167/144m², 14/16층, 남서향54.세안고 트인전망 깨끗",
      "price": "20억",
      "area": null,
      "floor": "16층",
      "deal_type": "매매",
      "extracted_at": "2025-07-18T11:28:44.621Z"
    },
    {
      "index": 17,
      "selector": ".item_link",
      "text": "성원상떼뷰(주상복합) 201동전세13억 5,000아파트167/144m², 7/16층, 남동향50 시스템에어컨 카페거리뷰 정자초 학원가 인프라굿",
      "price": "13억 5",
      "area": null,
      "floor": "16층",
      "deal_type": "전세",
      "extracted_at": "2025-07-18T11:28:44.621Z"
    },
    {
      "index": 31,
      "selector": "[class*=\"item\"]",
      "text": "전체면적㎡평전체100㎡167㎡170㎡187㎡205㎡209㎡",
      "price": null,
      "area": "100㎡",
      "floor": null,
      "deal_type": null,
      "extracted_at": "2025-07-18T11:28:44.622Z"
    }
  ],
  "transaction_history": [],
  "statistics": {
    "total_listings": 6,
    "total_transactions": 0,
    "data_quality": "enhanced"
  },
  "files": {
    "screenshot": "data/output/enhanced_screenshot_10203_20250718_202850.png"
  }
}