{
  "crawler_info": {
    "version": "2.0 Enhanced",
    "crawl_method": "stealth_mode",
    "crawled_at": "2025-07-18T03:28:18.866748",
    "complex_id": "2005"
  },
  "basic_info": {
    "complex_id": "2005",
    "source_url": "https://new.land.naver.com/complexes/2005",
    "extracted_at": "2025-07-18T03:28:15.539606",
    "url": "https://new.land.naver.com/complexes/2005?ms=37.413717,126.906684,17&a=APT:ABYG:JGC:PRE&e=RETAIL",
    "title": "네이버페이 부동산",
    "timestamp": "2025-07-17T18:28:13.144Z",
    "complexId": "2005"
  },
  "current_listings": [
    {
      "index": 0,
      "selector": ".item_link",
      "text": "적성3차 가동매매3억 6,600재건축70/64m², 6/6층, 남서향재건축.74타입 101동1901호확정. 25.6월말공사시작",
      "price": "3억 6",
      "area": null,
      "floor": "6층",
      "deal_type": "매매",
      "extracted_at": "2025-07-17T18:28:15.554Z"
    },
    {
      "index": 1,
      "selector": ".item_link",
      "text": "적성3차 가동매매3억 6,600재건축70/64m², 6/6층, 서향월판선만안역근처, 재건축진행중, 전용74.49 신청",
      "price": "3억 6",
      "area": null,
      "floor": "6층",
      "deal_type": "매매",
      "extracted_at": "2025-07-17T18:28:15.554Z"
    },
    {
      "index": 0,
      "selector": "[class*=\"deal\"]",
      "text": "거래방식거래방식전체매매전세월세단기임대중복선택이 가능합니다.전체",
      "price": null,
      "area": null,
      "floor": null,
      "deal_type": "매매",
      "extracted_at": "2025-07-17T18:28:15.556Z"
    },
    {
      "index": 4,
      "selector": "[class*=\"deal\"]",
      "text": "1,826만더파인타운(도시형)매매3.7억3.7억면적67㎡67.29㎡ ~ 67.29㎡매매매물만 보기1개 매물이 있습니다.단지정보",
      "price": "7억3",
      "area": "67㎡",
      "floor": null,
      "deal_type": "매매",
      "extracted_at": "2025-07-17T18:28:15.556Z"
    },
    {
      "index": 5,
      "selector": "[class*=\"deal\"]",
      "text": "1,427만서해(주상복합)매매3.8억3.8억면적88㎡88.68㎡ ~ 88.68㎡매매매물만 보기1개 매물이 있습니다.단지정보시세/실거래가",
      "price": "8억3",
      "area": "88㎡",
      "floor": null,
      "deal_type": "매매",
      "extracted_at": "2025-07-17T18:28:15.556Z"
    },
    {
      "index": 6,
      "selector": "[class*=\"deal\"]",
      "text": "2,079만미영팰리스매매4.59억4.59억면적73㎡73.31㎡ ~ 73.31㎡매매매물만 보기2개 매물이 있습니다.단지정보시세/실거래가",
      "price": "59억4",
      "area": "73㎡",
      "floor": null,
      "deal_type": "매매",
      "extracted_at": "2025-07-17T18:28:15.556Z"
    },
    {
      "index": 7,
      "selector": "[class*=\"deal\"]",
      "text": "1,605만영풍마드레빌매매5억4.4억~5.4억면적103㎡85.03㎡ ~ 103.5㎡매매매물만 보기24개 매물이 있습니다.단지정보시세/실거래가",
      "price": "5억4",
      "area": "103㎡",
      "floor": null,
      "deal_type": "매매",
      "extracted_at": "2025-07-17T18:28:15.556Z"
    },
    {
      "index": 8,
      "selector": "[class*=\"deal\"]",
      "text": "1,461만석수매매3.05억2.85억~3.1억월세70만70만면적69㎡69.75㎡ ~ 69.75㎡매매매물만 보기10개 매물이 있습니다.월세매물만 보기1개 매물이 있습니다.단지정보시세/실거래가",
      "price": "05억2",
      "area": "69㎡",
      "floor": null,
      "deal_type": "매매",
      "extracted_at": "2025-07-17T18:28:15.556Z"
    },
    {
      "index": 9,
      "selector": "[class*=\"deal\"]",
      "text": "2,827만안양자이더포레스트매매7.09억6.49억~8.3억면적83㎡82.85㎡ ~ 106.69㎡매매매물만 보기58개 매물이 있습니다.단지정보",
      "price": "09억6",
      "area": "83㎡",
      "floor": null,
      "deal_type": "매매",
      "extracted_at": "2025-07-17T18:28:15.556Z"
    },
    {
      "index": 10,
      "selector": "[class*=\"deal\"]",
      "text": "1,391만대림매매2.65억2.65억면적63㎡63.72㎡ ~ 63.72㎡매매매물만 보기1개 매물이 있습니다.단지정보",
      "price": "65억2",
      "area": "63㎡",
      "floor": null,
      "deal_type": "매매",
      "extracted_at": "2025-07-17T18:28:15.556Z"
    },
    {
      "index": 11,
      "selector": "[class*=\"deal\"]",
      "text": "2,018만삼우수피아(주상복합)매매4.7억4.4억~4.7억면적77㎡77.76㎡ ~ 77.76㎡매매매물만 보기5개 매물이 있습니다.단지정보시세/실거래가",
      "price": "7억4",
      "area": "77㎡",
      "floor": null,
      "deal_type": "매매",
      "extracted_at": "2025-07-17T18:28:15.556Z"
    },
    {
      "index": 12,
      "selector": "[class*=\"deal\"]",
      "text": "사랑채(도시형)면적 - ㎡54.17㎡ ~ 60.54㎡단지정보",
      "price": null,
      "area": "54.17㎡",
      "floor": null,
      "deal_type": null,
      "extracted_at": "2025-07-17T18:28:15.556Z"
    },
    {
      "index": 13,
      "selector": "[class*=\"deal\"]",
      "text": "1,236만원진매매4억4억면적107㎡107.29㎡ ~ 107.29㎡매매매물만 보기2개 매물이 있습니다.단지정보시세/실거래가",
      "price": "4억4",
      "area": "107㎡",
      "floor": null,
      "deal_type": "매매",
      "extracted_at": "2025-07-17T18:28:15.556Z"
    },
    {
      "index": 14,
      "selector": "[class*=\"deal\"]",
      "text": "1,862만무림매매4억3.5억~4.5억월세70만60만~70만면적71㎡71.18㎡ ~ 89.36㎡매매매물만 보기16개 매물이 있습니다.월세매물만 보기4개 매물이 있습니다.단지정보시세/실거래가",
      "price": "4억3",
      "area": "71㎡",
      "floor": null,
      "deal_type": "매매",
      "extracted_at": "2025-07-17T18:28:15.556Z"
    },
    {
      "index": 15,
      "selector": "[class*=\"deal\"]",
      "text": "1,804만적성3차매매3.82억3.66억~3.98억면적70㎡70.47㎡ ~ 70.47㎡매매매물만 보기4개 매물이 있습니다.단지정보시세/실거래가",
      "price": "82억3",
      "area": "70㎡",
      "floor": null,
      "deal_type": "매매",
      "extracted_at": "2025-07-17T18:28:15.556Z"
    },
    {
      "index": 16,
      "selector": "[class*=\"deal\"]",
      "text": "1,941만현대매매6.4억5.1억~8억전세4.2억4.2억면적109㎡83.35㎡ ~ 142.1㎡매매매물만 보기72개 매물이 있습니다.전세매물만 보기1개 매물이 있습니다.단지정보시세/실거래가",
      "price": "4억5",
      "area": "109㎡",
      "floor": null,
      "deal_type": "매매",
      "extracted_at": "2025-07-17T18:28:15.556Z"
    },
    {
      "index": 17,
      "selector": "[class*=\"deal\"]",
      "text": "성유하우스(도시형)면적 - ㎡29.67㎡ ~ 30.39㎡단지정보",
      "price": null,
      "area": "29.67㎡",
      "floor": null,
      "deal_type": null,
      "extracted_at": "2025-07-17T18:28:15.556Z"
    },
    {
      "index": 18,
      "selector": "[class*=\"deal\"]",
      "text": "신흥면적86.15㎡77.74㎡ ~ 86.15㎡단지정보시세/실거래가",
      "price": null,
      "area": "86.15㎡",
      "floor": null,
      "deal_type": null,
      "extracted_at": "2025-07-17T18:28:15.556Z"
    },
    {
      "index": 19,
      "selector": "[class*=\"deal\"]",
      "text": "예다음(도시형)면적 - ㎡41.56㎡ ~ 58.17㎡단지정보",
      "price": null,
      "area": "41.56㎡",
      "floor": null,
      "deal_type": null,
      "extracted_at": "2025-07-17T18:28:15.556Z"
    },
    {
      "index": 20,
      "selector": "[class*=\"deal\"]",
      "text": "1,653만개성하이뷰(280-15)매매4억4억면적80㎡80.3㎡ ~ 80.3㎡매매매물만 보기2개 매물이 있습니다.단지정보",
      "price": "4억4",
      "area": "80㎡",
      "floor": null,
      "deal_type": "매매",
      "extracted_at": "2025-07-17T18:28:15.556Z"
    },
    {
      "index": 21,
      "selector": "[class*=\"deal\"]",
      "text": "1,488만대교매매2.7억2.7억면적60㎡60.3㎡ ~ 60.3㎡매매매물만 보기1개 매물이 있습니다.단지정보",
      "price": "7억2",
      "area": "60㎡",
      "floor": null,
      "deal_type": "매매",
      "extracted_at": "2025-07-17T18:28:15.556Z"
    },
    {
      "index": 22,
      "selector": "[class*=\"deal\"]",
      "text": "2,098만더파인캐슬매매3.3억3.3억~3.7억면적52㎡52.1㎡ ~ 60.67㎡매매매물만 보기3개 매물이 있습니다.단지정보",
      "price": "3억3",
      "area": "52㎡",
      "floor": null,
      "deal_type": "매매",
      "extracted_at": "2025-07-17T18:28:15.556Z"
    },
    {
      "index": 23,
      "selector": "[class*=\"deal\"]",
      "text": "1,782만경일매매3.45억3억~3.8억전세-1.7억월세-40만면적64㎡64.69㎡ ~ 71.02㎡매매매물만 보기5개 매물이 있습니다.전세매물만 보기1개 매물이 있습니다.월세매물만 보기1개 매물이 있습니다.단지정보시세/실거래가",
      "price": "45억3",
      "area": "64㎡",
      "floor": null,
      "deal_type": "매매",
      "extracted_at": "2025-07-17T18:28:15.556Z"
    },
    {
      "index": 24,
      "selector": "[class*=\"deal\"]",
      "text": "1,934만관악역우방유쉘매매8.25억8억~8.9억면적141㎡141.45㎡ ~ 141.45㎡매매매물만 보기6개 매물이 있습니다.단지정보시세/실거래가",
      "price": "25억8",
      "area": "141㎡",
      "floor": null,
      "deal_type": "매매",
      "extracted_at": "2025-07-17T18:28:15.556Z"
    },
    {
      "index": 26,
      "selector": "[class*=\"deal\"]",
      "text": "해맑음(도시형)면적 - ㎡51.71㎡ ~ 55.74㎡단지정보",
      "price": null,
      "area": "51.71㎡",
      "floor": null,
      "deal_type": null,
      "extracted_at": "2025-07-17T18:28:15.556Z"
    },
    {
      "index": 28,
      "selector": "[class*=\"deal\"]",
      "text": "1,820만일곡숲(도시형)매매4.9억3.25억~4.9억면적89㎡73.05㎡ ~ 90.32㎡매매매물만 보기5개 매물이 있습니다.단지정보",
      "price": "9억3",
      "area": "89㎡",
      "floor": null,
      "deal_type": "매매",
      "extracted_at": "2025-07-17T18:28:15.556Z"
    }
  ],
  "transaction_history": [],
  "statistics": {
    "total_listings": 26,
    "total_transactions": 0,
    "data_quality": "enhanced"
  },
  "files": {
    "screenshot": "data/output/enhanced_screenshot_2005_20250718_032818.png"
  }
}