{
  "crawler_info": {
    "version": "2.0 Enhanced",
    "crawl_method": "stealth_mode",
    "crawled_at": "2025-07-17T22:44:46.270562",
    "complex_id": "1135"
  },
  "basic_info": {
    "complex_id": "1135",
    "source_url": "https://new.land.naver.com/complexes/1135",
    "extracted_at": "2025-07-17T22:44:40.922543",
    "url": "https://new.land.naver.com/complexes/1135?ms=37.488795,126.977406,17&a=APT:ABYG:JGC:PRE&e=RETAIL",
    "title": "네이버페이 부동산",
    "timestamp": "2025-07-17T13:44:38.878Z",
    "complexId": "1135"
  },
  "current_listings": [
    {
      "index": 0,
      "selector": ".item_link",
      "text": "집주인대아3차(경남아너스빌) 601동매매6억 4,000아파트59/42m², 2/11층, 남향더블 역세권  올수리  세안고",
      "price": "6억 4",
      "area": null,
      "floor": "11층",
      "deal_type": "매매",
      "extracted_at": "2025-07-17T13:44:40.938Z"
    },
    {
      "index": 1,
      "selector": ".item_link",
      "text": "집주인대아3차(경남아너스빌) 601동매매12억 5,000아파트136/110m², 8/11층, 동향",
      "price": "12억 5",
      "area": null,
      "floor": "11층",
      "deal_type": "매매",
      "extracted_at": "2025-07-17T13:44:40.938Z"
    },
    {
      "index": 8,
      "selector": ".item_link",
      "text": "집주인대아3차(경남아너스빌) 601동매매13억 3,000아파트136/110m², 3/11층, 동향지하철5분거리 특올수리",
      "price": "13억 3",
      "area": null,
      "floor": "11층",
      "deal_type": "매매",
      "extracted_at": "2025-07-17T13:44:40.938Z"
    },
    {
      "index": 17,
      "selector": ".item_link",
      "text": "대아3차(경남아너스빌) 601동매매12억 5,000아파트136/110m², 8/11층, 남향대아아파트 110타입 입주가능한 4룸 매매",
      "price": "12억 5",
      "area": null,
      "floor": "11층",
      "deal_type": "매매",
      "extracted_at": "2025-07-17T13:44:40.938Z"
    },
    {
      "index": 19,
      "selector": ".item_link",
      "text": "대아3차(경남아너스빌) 601동매매6억 6,000아파트59/42m², 6/11층, 남동향이수역세권 세안고  상태매우양호",
      "price": "6억 6",
      "area": null,
      "floor": "11층",
      "deal_type": "매매",
      "extracted_at": "2025-07-17T13:44:40.938Z"
    }
  ],
  "transaction_history": [],
  "statistics": {
    "total_listings": 5,
    "total_transactions": 0,
    "data_quality": "enhanced"
  },
  "files": {
    "screenshot": "data/output/enhanced_screenshot_1135_20250717_224446.png"
  }
}